imteksimfw/__init__.py
imteksimfw/version.py
imteksimfw/fireworks/__init__.py
imteksimfw/fireworks/user_objects/__init__.py
imteksimfw/fireworks/user_objects/firetasks/__init__.py
imteksimfw/fireworks/user_objects/firetasks/cmd_tasks.py
imteksimfw/fireworks/user_objects/firetasks/dataflow_tasks.py
imteksimfw/fireworks/user_objects/firetasks/dtool_lookup_tasks.py
imteksimfw/fireworks/user_objects/firetasks/dtool_tasks.py
imteksimfw/fireworks/user_objects/firetasks/recover_tasks.py
imteksimfw/fireworks/user_objects/firetasks/ssh_tasks.py
imteksimfw/fireworks/user_objects/firetasks/storage_tasks.py
imteksimfw/fireworks/user_objects/firetasks/doc/recover_tasks_1.txt
imteksimfw/fireworks/user_objects/firetasks/doc/recover_tasks_2.txt
imteksimfw/fireworks/user_objects/firetasks/doc/recover_tasks_3.txt
imteksimfw/fireworks/user_objects/firetasks/doc/recover_tasks_4.txt
imteksimfw/fireworks/user_objects/firetasks/doc/recover_tasks_5.txt
imteksimfw/utils/__init__.py
imteksimfw/utils/dict.py
imteksimfw/utils/environ.py
imteksimfw/utils/logging.py
imteksimfw/utils/multiprocessing.py
imteksimfw/utils/serialize.py
imteksimfw/utils/tracer.py
imteksimfw-0.5.1.dist-info/LICENSE
imteksimfw-0.5.1.dist-info/METADATA
imteksimfw-0.5.1.dist-info/WHEEL
imteksimfw-0.5.1.dist-info/top_level.txt
imteksimfw-0.5.1.dist-info/RECORD
