Metadata-Version: 2.1
Name: imteksimfw
Version: 0.5.1
Summary: Fireworks additions
Home-page: https://github.com/IMTEK-Simulation/imteksimfw
Download-URL: https://github.com/IMTEK-Simulation/imteksimfw/tarball/0.5.1
Author: Johannes Laurin Hoermann
Author-email: johannes.hoermann@imtek.uni-freiburg.de
License: MIT
Platform: UNKNOWN
Requires-Python: >=3.6.5
License-File: LICENSE
Requires-Dist: dill (>=0.3.1.1dtoolcore>=3.17.0)
Requires-Dist: dtool-create (>=0.23.0)
Requires-Dist: dtool-lookup-api (>=0.1.0)
Requires-Dist: fireworks (>=1.9.5)
Requires-Dist: jinja2 (>=2.10)
Requires-Dist: jinja2-time (>=0.2.0)
Requires-Dist: monty (>=4.0.2)
Requires-Dist: paramiko (>=2.4.2)
Requires-Dist: six (>=1.15.0)
Requires-Dist: ruamel.yaml (>=0.16.12)
Provides-Extra: testing
Requires-Dist: mock-ssh-server (>=0.8.1) ; extra == 'testing'
Requires-Dist: dtool-smb (>=0.1.0) ; extra == 'testing'
Requires-Dist: requests (>=2.24.0) ; extra == 'testing'
Requires-Dist: urllib3 (<1.26,>=1.25.11) ; extra == 'testing'
Requires-Dist: dtool-lookup-server (>=0.15.0) ; extra == 'testing'
Requires-Dist: dtool-lookup-server-direct-mongo-plugin (>=0.1.2) ; extra == 'testing'
